odoo10_addon_openeducat_support-10.0.3.0.0-py2.7-nspkg.pth
odoo/addons/openeducat_support/README.rst
odoo/addons/openeducat_support/__init__.py
odoo/addons/openeducat_support/__manifest__.py
odoo/addons/openeducat_support/static/description/icon.png
odoo/addons/openeducat_support/static/description/index.html
odoo/addons/openeducat_support/static/description/openeducat_logo.png
odoo/addons/openeducat_support/static/description/openeducat_support_banner.jpg
odoo/addons/openeducat_support/static/src/js/user_menu.js
odoo/addons/openeducat_support/static/src/xml/web.xml
odoo/addons/openeducat_support/static/src/xml/web_planner.xml
odoo/addons/openeducat_support/views/web_planner_templates.xml
odoo10_addon_openeducat_support-10.0.3.0.0.dist-info/DESCRIPTION.rst
odoo10_addon_openeducat_support-10.0.3.0.0.dist-info/METADATA
odoo10_addon_openeducat_support-10.0.3.0.0.dist-info/RECORD
odoo10_addon_openeducat_support-10.0.3.0.0.dist-info/WHEEL
odoo10_addon_openeducat_support-10.0.3.0.0.dist-info/metadata.json
odoo10_addon_openeducat_support-10.0.3.0.0.dist-info/namespace_packages.txt
odoo10_addon_openeducat_support-10.0.3.0.0.dist-info/top_level.txt
